NiukeShejiGangQiuzhiJingyanFenxiang20212022/README.md
NiukeShejiGangQiuzhiJingyanFenxiang20212022/__init__.py
NiukeShejiGangQiuzhiJingyanFenxiang20212022/__main__.py
NiukeShejiGangQiuzhiJingyanFenxiang20212022/file.epub
NiukeShejiGangQiuzhiJingyanFenxiang20212022/index.html
NiukeShejiGangQiuzhiJingyanFenxiang20212022/css/__init__.py
NiukeShejiGangQiuzhiJingyanFenxiang20212022/css/annotations.css
NiukeShejiGangQiuzhiJingyanFenxiang20212022/css/main.css
NiukeShejiGangQiuzhiJingyanFenxiang20212022/css/normalize.css
NiukeShejiGangQiuzhiJingyanFenxiang20212022/css/popup.css
NiukeShejiGangQiuzhiJingyanFenxiang20212022/font/__init__.py
NiukeShejiGangQiuzhiJingyanFenxiang20212022/font/fontello.eot
NiukeShejiGangQiuzhiJingyanFenxiang20212022/font/fontello.svg
NiukeShejiGangQiuzhiJingyanFenxiang20212022/font/fontello.ttf
NiukeShejiGangQiuzhiJingyanFenxiang20212022/font/fontello.woff
NiukeShejiGangQiuzhiJingyanFenxiang20212022/img/__init__.py
NiukeShejiGangQiuzhiJingyanFenxiang20212022/img/annotator-glyph-sprite.png
NiukeShejiGangQiuzhiJingyanFenxiang20212022/img/annotator-icon-sprite.png
NiukeShejiGangQiuzhiJingyanFenxiang20212022/img/apple-touch-icon.png
NiukeShejiGangQiuzhiJingyanFenxiang20212022/img/cancelfullscreen.png
NiukeShejiGangQiuzhiJingyanFenxiang20212022/img/close.png
NiukeShejiGangQiuzhiJingyanFenxiang20212022/img/fullscreen.png
NiukeShejiGangQiuzhiJingyanFenxiang20212022/img/loader.gif
NiukeShejiGangQiuzhiJingyanFenxiang20212022/img/menu-icon.png
NiukeShejiGangQiuzhiJingyanFenxiang20212022/img/save.png
NiukeShejiGangQiuzhiJingyanFenxiang20212022/img/saved.png
NiukeShejiGangQiuzhiJingyanFenxiang20212022/img/settings-s.png
NiukeShejiGangQiuzhiJingyanFenxiang20212022/img/settings.png
NiukeShejiGangQiuzhiJingyanFenxiang20212022/img/star.png
NiukeShejiGangQiuzhiJingyanFenxiang20212022/js/__init__.py
NiukeShejiGangQiuzhiJingyanFenxiang20212022/js/epub.js
NiukeShejiGangQiuzhiJingyanFenxiang20212022/js/epub.min.js
niuke_sheji_gang_qiuzhi_jingyan_fenxiang_2021_2022-2024.3.6.0.dist-info/METADATA
niuke_sheji_gang_qiuzhi_jingyan_fenxiang_2021_2022-2024.3.6.0.dist-info/WHEEL
niuke_sheji_gang_qiuzhi_jingyan_fenxiang_2021_2022-2024.3.6.0.dist-info/entry_points.txt
niuke_sheji_gang_qiuzhi_jingyan_fenxiang_2021_2022-2024.3.6.0.dist-info/top_level.txt
niuke_sheji_gang_qiuzhi_jingyan_fenxiang_2021_2022-2024.3.6.0.dist-info/RECORD
